torchpairwise/_C.cpython-310-x86_64-linux-gnu.so
torchpairwise/__init__.py
torchpairwise/_ops.py
torchpairwise/_version.py
torchpairwise/extension.py
torchpairwise/csrc/torchpairwise.cpp
torchpairwise/csrc/ops/additive_chi2_kernel.cpp
torchpairwise/csrc/ops/braycurtis.cpp
torchpairwise/csrc/ops/canberra.cpp
torchpairwise/csrc/ops/cpdist.cpp
torchpairwise/csrc/ops/hausdorff.cpp
torchpairwise/csrc/ops/haversine.cpp
torchpairwise/csrc/ops/neighbors.cpp
torchpairwise/csrc/ops/pairwise_binary.cpp
torchpairwise/csrc/ops/pairwise_metrics.cpp
torchpairwise/csrc/ops/ppminkowski.cpp
torchpairwise/csrc/ops/prf_div.cpp
torchpairwise/csrc/ops/snr.cpp
torchpairwise/csrc/ops/sqjensenshannon.cpp
torchpairwise/csrc/ops/sqmahalanobis.cpp
torchpairwise/csrc/ops/wminkowski.cpp
torchpairwise/csrc/ops/autograd/additive_chi2_kernel.cpp
torchpairwise/csrc/ops/autograd/braycurtis_kernel.cpp
torchpairwise/csrc/ops/autograd/canberra_kernel.cpp
torchpairwise/csrc/ops/autograd/hausdorff_kernel.cpp
torchpairwise/csrc/ops/autograd/haversine_kernel.cpp
torchpairwise/csrc/ops/autograd/ppminkowski_kernel.cpp
torchpairwise/csrc/ops/autograd/prf_div_kernel.cpp
torchpairwise/csrc/ops/autograd/snr_kernel.cpp
torchpairwise/csrc/ops/autograd/sqjensenshannon_kernel.cpp
torchpairwise/csrc/ops/autograd/sqmahalanobis_kernel.cpp
torchpairwise/csrc/ops/autograd/wminkowski_kernel.cpp
torchpairwise/csrc/ops/cpu/additive_chi2_kernel.cpp
torchpairwise/csrc/ops/cpu/braycurtis_kernel.cpp
torchpairwise/csrc/ops/cpu/canberra_kernel.cpp
torchpairwise/csrc/ops/cpu/hausdorff_kernel.cpp
torchpairwise/csrc/ops/cpu/haversine_kernel.cpp
torchpairwise/csrc/ops/cpu/pairwise_binary_kernels.cpp
torchpairwise/csrc/ops/cpu/ppminkowski_kernel.cpp
torchpairwise/csrc/ops/cpu/prf_div_kernel.cpp
torchpairwise/csrc/ops/cpu/snr_kernel.cpp
torchpairwise/csrc/ops/cpu/sqjensenshannon_kernel.cpp
torchpairwise/csrc/ops/cpu/sqmahalanobis_kernel.cpp
torchpairwise/csrc/ops/cpu/wminkowski_kernel.cpp
torchpairwise-0.3.0.dist-info/METADATA
torchpairwise-0.3.0.dist-info/WHEEL
torchpairwise-0.3.0.dist-info/top_level.txt
torchpairwise-0.3.0.dist-info/RECORD
torchpairwise-0.3.0.dist-info/licenses/LICENSE.txt
