Metadata-Version: 2.4
Name: torchpairwise
Version: 0.3.0
Summary: Pairwise Metrics for PyTorch
Home-page: https://github.com/inspiros/torchpairwise
Author: Hoang-Nhat Tran (inspiros)
Author-email: hnhat.tran@gmail.com
License: MIT
Project-URL: Source, https://github.com/inspiros/torchpairwise
Keywords: pairwise_metric,pairwise_distance,kernel_function
Classifier: Development Status :: 4 - Beta
Classifier: Environment :: GPU :: NVIDIA CUDA :: 12
Classifier: Intended Audience :: Developers
Classifier: Intended Audience :: Education
Classifier: Intended Audience :: Science/Research
Classifier: License :: OSI Approved :: MIT License
Classifier: Programming Language :: Python :: 3
Classifier: Programming Language :: Python :: 3 :: Only
Classifier: Programming Language :: Python :: 3.9
Classifier: Programming Language :: Python :: 3.10
Classifier: Programming Language :: Python :: 3.11
Classifier: Programming Language :: Python :: 3.12
Classifier: Programming Language :: Python :: 3.13
Classifier: Operating System :: OS Independent
Classifier: Topic :: Scientific/Engineering :: Mathematics
Classifier: Topic :: Scientific/Engineering :: Artificial Intelligence
Requires-Python: >=3.9
License-File: LICENSE.txt
Requires-Dist: torch<2.8.0,>=2.7.0
Provides-Extra: examples
Requires-Dist: scipy; extra == "examples"
Requires-Dist: scikit-learn; extra == "examples"
Requires-Dist: tqdm; extra == "examples"
Provides-Extra: tests
Requires-Dist: scipy; extra == "tests"
Requires-Dist: scikit-learn; extra == "tests"
Requires-Dist: tqdm; extra == "tests"
Dynamic: license-file
